{
  "name": "groomit-modern",
  "type": "light",
  "colors": {
    "background": {
      "DEFAULT": "0 0% 100%",
      "foreground": "224 71.4% 4.1%"
    },
    "primary": {
      "DEFAULT": "267 75% 40%",
      "foreground": "0 0% 98%"
    },
    "secondary": {
      "DEFAULT": "267 60% 35%",
      "foreground": "0 0% 98%"
    },
    "muted": {
      "DEFAULT": "267 10% 96%",
      "foreground": "267 30% 46%"
    },
    "accent": {
      "DEFAULT": "267 59% 94%",
      "foreground": "267 75% 40%"
    },
    "destructive": {
      "DEFAULT": "0 84.2% 60.2%",
      "foreground": "0 0% 98%"
    },
    "success": {
      "DEFAULT": "142.1 76.2% 36.3%",
      "foreground": "0 0% 98%"
    },
    "warning": {
      "DEFAULT": "38 92% 50%",
      "foreground": "0 0% 98%"
    },
    "card": {
      "DEFAULT": "0 0% 100%",
      "foreground": "224 71.4% 4.1%"
    },
    "popover": {
      "DEFAULT": "0 0% 100%",
      "foreground": "224 71.4% 4.1%"
    },
    "dialog": {
      "DEFAULT": "0 0% 100%",
      "foreground": "224 71.4% 4.1%",
      "overlay": "0 0% 0% / 50%"
    },
    "border": "220 13% 91%",
    "input": "220 13% 91%",
    "ring": "267 75% 40%"
  },
  "borderRadius": {
    "lg": "0.75rem",
    "md": "0.5rem",
    "sm": "0.375rem",
    "xl": "1rem",
    "2xl": "1.5rem"
  },
  "font": {
    "sans": ["Inter", "sans-serif"]
  }
}
